textblob/__init__.py
textblob/_text.py
textblob/base.py
textblob/blob.py
textblob/classifiers.py
textblob/compat.py
textblob/decorators.py
textblob/download_corpora.py
textblob/exceptions.py
textblob/formats.py
textblob/inflect.py
textblob/mixins.py
textblob/np_extractors.py
textblob/parsers.py
textblob/sentiments.py
textblob/taggers.py
textblob/tokenizers.py
textblob/translate.py
textblob/utils.py
textblob/wordnet.py
textblob/en/__init__.py
textblob/en/en-context.txt
textblob/en/en-entities.txt
textblob/en/en-lexicon.txt
textblob/en/en-morphology.txt
textblob/en/en-sentiment.xml
textblob/en/en-spelling.txt
textblob/en/inflect.py
textblob/en/np_extractors.py
textblob/en/parsers.py
textblob/en/sentiments.py
textblob/en/taggers.py
textblob/unicodecsv/__init__.py
textblob-0.17.0.dist-info/AUTHORS.rst
textblob-0.17.0.dist-info/LICENSE
textblob-0.17.0.dist-info/METADATA
textblob-0.17.0.dist-info/NOTICE
textblob-0.17.0.dist-info/WHEEL
textblob-0.17.0.dist-info/top_level.txt
textblob-0.17.0.dist-info/RECORD
